pyesef/VERSION
pyesef/__init__.py
pyesef/__main__.py
pyesef/const.py
pyesef/error.py
pyesef/py.typed
pyesef/utils.py
pyesef/helpers/__init__.py
pyesef/helpers/download_package.py
pyesef/helpers/extract_definitions_to_csv.py
pyesef/helpers/read_and_save_filings.py
pyesef/helpers/read_facts.py
pyesef-1.0.2.dist-info/LICENSE
pyesef-1.0.2.dist-info/METADATA
pyesef-1.0.2.dist-info/WHEEL
pyesef-1.0.2.dist-info/top_level.txt
pyesef-1.0.2.dist-info/RECORD
