Metadata-Version: 2.1
Name: pyesef
Version: 1.0.2
Home-page: https://github.com/ggravlingen/pyesef
Download-URL: https://github.com/ggravlingen/pyesef/archive/1.0.2.zip
Author: ggravlingen
Author-email: no@email.com
License: MIT
Keywords: esef financial statement
Classifier: Natural Language :: English
Classifier: Programming Language :: Python :: 3
Classifier: Programming Language :: Python :: 3.9
Classifier: Programming Language :: Python :: 3.10
Classifier: Intended Audience :: Financial and Insurance Industry
Requires-Python: >=3.9
License-File: LICENSE
